kseal/__init__.py
kseal/__main__.py
kseal/binary.py
kseal/cli.py
kseal/config.py
kseal/decrypt.py
kseal/exceptions.py
kseal/github.py
kseal/secrets.py
kseal/settings.py
kseal/yaml_utils.py
kseal/services/__init__.py
kseal/services/filesystem.py
kseal/services/kubernetes.py
kseal/services/kubeseal.py
kseal-2.0.2.dist-info/METADATA
kseal-2.0.2.dist-info/WHEEL
kseal-2.0.2.dist-info/entry_points.txt
kseal-2.0.2.dist-info/licenses/LICENSE
kseal-2.0.2.dist-info/RECORD
