Metadata-Version: 2.4
Name: kseal
Version: 2.0.2
Summary: A kubeseal companion CLI - decrypt, export, and encrypt Kubernetes Secrets with automatic binary management
Author-email: Bruno Bernard <contact.brunobernard@gmail.com>
License: MIT
License-File: LICENSE
Keywords: cli,kubernetes,kubeseal,sealed-secrets,secrets
Classifier: Development Status :: 5 - Production/Stable
Classifier: Environment :: Console
Classifier: Intended Audience :: Developers
Classifier: Intended Audience :: System Administrators
Classifier: License :: OSI Approved :: MIT License
Classifier: Operating System :: MacOS
Classifier: Operating System :: POSIX :: Linux
Classifier: Programming Language :: Python :: 3
Classifier: Programming Language :: Python :: 3.12
Classifier: Topic :: System :: Systems Administration
Classifier: Topic :: Utilities
Requires-Python: >=3.12
Requires-Dist: click>=8.0
Requires-Dist: httpx>=0.25
Requires-Dist: kubernetes>=28.0
Requires-Dist: packaging>=23.0
Requires-Dist: pydantic>=2.0
Requires-Dist: rich>=14.2.0
Requires-Dist: ruamel-yaml>=0.18
